easy_decorator/__init__.py
easy_decorator/exceptions.py
easy_decorator/async_decorators/__init__.py
easy_decorator/async_decorators/basic.py
easy_decorator/class_decorators/__init__.py
easy_decorator/class_decorators/basic.py
easy_decorator/core/__init__.py
easy_decorator/core/base.py
easy_decorator/function/__init__.py
easy_decorator/function/basic.py
easy_decorator/utils/__init__.py
easy_decorator/utils/helpers.py
Easys_Decorator-0.1.2.dist-info/METADATA
Easys_Decorator-0.1.2.dist-info/WHEEL
Easys_Decorator-0.1.2.dist-info/top_level.txt
Easys_Decorator-0.1.2.dist-info/RECORD
