Metadata-Version: 2.1
Name: Easys-Decorator
Version: 0.1.2
Summary: A library to simplify decorators in Python
Home-page: https://github.com/SoulCodingYanhun/Easy-Decorator
Author: SoulCodingYanhun
Author-email: zhuzhishengzhu6@outlook.com
Classifier: Development Status :: 3 - Alpha
Classifier: Intended Audience :: Developers
Classifier: License :: OSI Approved :: MIT License
Classifier: Operating System :: OS Independent
Classifier: Programming Language :: Python :: 3
Classifier: Programming Language :: Python :: 3.6
Classifier: Programming Language :: Python :: 3.7
Classifier: Programming Language :: Python :: 3.8
Classifier: Programming Language :: Python :: 3.9
Requires-Python: >=3.6
